psn_monitor.py
psn_monitor-1.8.dist-info/licenses/LICENSE
psn_monitor-1.8.dist-info/METADATA
psn_monitor-1.8.dist-info/WHEEL
psn_monitor-1.8.dist-info/entry_points.txt
psn_monitor-1.8.dist-info/top_level.txt
psn_monitor-1.8.dist-info/RECORD
