Metadata-Version: 2.4
Name: psn_monitor
Version: 1.8
Summary: Tool implementing real-time tracking of Sony PlayStation (PSN) players activities
Author-email: Michal Szymanski <misiektoja-pypi@rm-rf.ninja>
License-Expression: GPL-3.0-or-later
Project-URL: Homepage, https://github.com/misiektoja/psn_monitor
Project-URL: Source, https://github.com/misiektoja/psn_monitor
Project-URL: Changelog, https://github.com/misiektoja/psn_monitor/blob/main/RELEASE_NOTES.md
Keywords: psn,playstation,monitoring,tracking,real-time,osint,psnawp
Classifier: Programming Language :: Python :: 3
Classifier: Operating System :: OS Independent
Classifier: Operating System :: Microsoft :: Windows
Classifier: Operating System :: POSIX :: Linux
Classifier: Operating System :: MacOS :: MacOS X
Requires-Python: >=3.10
License-File: LICENSE
Requires-Dist: PSNAWP>=2.0.0
Requires-Dist: requests>=2.0
Requires-Dist: python-dateutil>=2.8
Requires-Dist: pytz>=2020.1
Requires-Dist: tzlocal>=4.0
Requires-Dist: python-dotenv>=0.19
Dynamic: license-file
